yk_face/__init__.py
yk_face/face.py
yk_face/group.py
yk_face/util.py
yk_face-0.3.6.dist-info/LICENSE
yk_face-0.3.6.dist-info/METADATA
yk_face-0.3.6.dist-info/WHEEL
yk_face-0.3.6.dist-info/top_level.txt
yk_face-0.3.6.dist-info/RECORD
