Metadata-Version: 2.1
Name: yk_face
Version: 0.3.6
Summary: Python SDK for the YouFace API.
Home-page: https://github.com/dev-yoonik/YK-Face-Python
Author: Youverse
Author-email: tech@youverse.id
License: MIT
Classifier: Programming Language :: Python :: 3
Classifier: License :: OSI Approved :: MIT License
Classifier: Operating System :: OS Independent
Requires-Python: >=3.8
License-File: LICENSE
Requires-Dist: yk-face-api-model <4,>=3.0.4
Requires-Dist: yk-utils <2,>=1.3.1
Provides-Extra: tests
Requires-Dist: pytest ; extra == 'tests'
